{
  "schemaVersion": 1,
  "generatedAt": "2026-05-28T13:30:07Z",
  "backlogThresholdMin": 10,
  "staleThresholdMin": 30,
  "global": {
    "backlogEquivProducts": 3706.75,
    "backlogOrdersOpen": 8,
    "totalOrdersToday": 1290,
    "backlogOrdersToday": 38,
    "backlogRatePercent": 2.95
  },
  "byStore": [
    {
      "shopNumber": "US00001",
      "backlogEquivProducts": 1025.25,
      "backlogOrdersOpen": 0,
      "totalOrdersToday": 0,
      "backlogOrdersToday": 0
    },
    {
      "shopNumber": "US00002",
      "backlogEquivProducts": 507.0,
      "backlogOrdersOpen": 1,
      "totalOrdersToday": 110,
      "backlogOrdersToday": 1
    },
    {
      "shopNumber": "US00003",
      "backlogEquivProducts": 196.75,
      "backlogOrdersOpen": 1,
      "totalOrdersToday": 91,
      "backlogOrdersToday": 1
    },
    {
      "shopNumber": "US00004",
      "backlogEquivProducts": 350.75,
      "backlogOrdersOpen": 2,
      "totalOrdersToday": 222,
      "backlogOrdersToday": 26
    },
    {
      "shopNumber": "US00005",
      "backlogEquivProducts": 430.25,
      "backlogOrdersOpen": 1,
      "totalOrdersToday": 101,
      "backlogOrdersToday": 1
    },
    {
      "shopNumber": "US00006",
      "backlogEquivProducts": 390.5,
      "backlogOrdersOpen": 1,
      "totalOrdersToday": 142,
      "backlogOrdersToday": 4
    },
    {
      "shopNumber": "US00008",
      "backlogEquivProducts": 144.0,
      "backlogOrdersOpen": 1,
      "totalOrdersToday": 136,
      "backlogOrdersToday": 1
    },
    {
      "shopNumber": "US00012",
      "backlogEquivProducts": 50.0,
      "backlogOrdersOpen": 0,
      "totalOrdersToday": 48,
      "backlogOrdersToday": 0
    },
    {
      "shopNumber": "US00020",
      "backlogEquivProducts": 64.0,
      "backlogOrdersOpen": 0,
      "totalOrdersToday": 53,
      "backlogOrdersToday": 0
    },
    {
      "shopNumber": "US00024",
      "backlogEquivProducts": 156.5,
      "backlogOrdersOpen": 1,
      "totalOrdersToday": 91,
      "backlogOrdersToday": 1
    },
    {
      "shopNumber": "US00025",
      "backlogEquivProducts": 304.0,
      "backlogOrdersOpen": 0,
      "totalOrdersToday": 108,
      "backlogOrdersToday": 3
    },
    {
      "shopNumber": "US00027",
      "backlogEquivProducts": 87.75,
      "backlogOrdersOpen": 0,
      "totalOrdersToday": 188,
      "backlogOrdersToday": 0
    }
  ]
}
