{
  "schemaVersion": 1,
  "generatedAt": "2026-05-31T20:30:07Z",
  "backlogThresholdMin": 10,
  "staleThresholdMin": 30,
  "global": {
    "backlogEquivProducts": 3725.75,
    "backlogOrdersOpen": 7,
    "totalOrdersToday": 2254,
    "backlogOrdersToday": 13,
    "backlogRatePercent": 0.58
  },
  "byStore": [
    {
      "shopNumber": "US00001",
      "backlogEquivProducts": 1026.25,
      "backlogOrdersOpen": 1,
      "totalOrdersToday": 275,
      "backlogOrdersToday": 2
    },
    {
      "shopNumber": "US00002",
      "backlogEquivProducts": 508.0,
      "backlogOrdersOpen": 0,
      "totalOrdersToday": 187,
      "backlogOrdersToday": 0
    },
    {
      "shopNumber": "US00003",
      "backlogEquivProducts": 199.75,
      "backlogOrdersOpen": 1,
      "totalOrdersToday": 148,
      "backlogOrdersToday": 1
    },
    {
      "shopNumber": "US00004",
      "backlogEquivProducts": 350.75,
      "backlogOrdersOpen": 0,
      "totalOrdersToday": 172,
      "backlogOrdersToday": 0
    },
    {
      "shopNumber": "US00005",
      "backlogEquivProducts": 439.25,
      "backlogOrdersOpen": 1,
      "totalOrdersToday": 285,
      "backlogOrdersToday": 4
    },
    {
      "shopNumber": "US00006",
      "backlogEquivProducts": 394.5,
      "backlogOrdersOpen": 3,
      "totalOrdersToday": 234,
      "backlogOrdersToday": 5
    },
    {
      "shopNumber": "US00008",
      "backlogEquivProducts": 142.0,
      "backlogOrdersOpen": 0,
      "totalOrdersToday": 94,
      "backlogOrdersToday": 0
    },
    {
      "shopNumber": "US00012",
      "backlogEquivProducts": 50.0,
      "backlogOrdersOpen": 0,
      "totalOrdersToday": 136,
      "backlogOrdersToday": 0
    },
    {
      "shopNumber": "US00020",
      "backlogEquivProducts": 65.0,
      "backlogOrdersOpen": 0,
      "totalOrdersToday": 142,
      "backlogOrdersToday": 0
    },
    {
      "shopNumber": "US00024",
      "backlogEquivProducts": 156.5,
      "backlogOrdersOpen": 0,
      "totalOrdersToday": 119,
      "backlogOrdersToday": 0
    },
    {
      "shopNumber": "US00025",
      "backlogEquivProducts": 306.0,
      "backlogOrdersOpen": 1,
      "totalOrdersToday": 404,
      "backlogOrdersToday": 1
    },
    {
      "shopNumber": "US00027",
      "backlogEquivProducts": 87.75,
      "backlogOrdersOpen": 0,
      "totalOrdersToday": 58,
      "backlogOrdersToday": 0
    }
  ]
}
